Metadata-Version: 2.1
Name: funfact
Version: 1.0.1
Summary: Functional factorization for matrices and tensors
Home-page: https://github.com/yhtang/FunFact
Author: Yu-Hang Tang
Author-email: Tang.Maxin@gmail.com
License: BSD
Platform: any
Classifier: Programming Language :: Python
Classifier: Development Status :: 5 - Production/Stable
Classifier: Natural Language :: English
Classifier: Environment :: Console
Classifier: Intended Audience :: End Users/Desktop
Classifier: Intended Audience :: Science/Research
Classifier: Operating System :: OS Independent
Classifier: Programming Language :: Python
Classifier: Topic :: Scientific/Engineering
Classifier: Topic :: Scientific/Engineering :: Mathematics
Classifier: Topic :: Software Development :: Libraries
Classifier: Topic :: Software Development :: Libraries :: Python Modules
Requires-Python: >=3.7
Provides-Extra: jax
Provides-Extra: torch
Provides-Extra: docs
Provides-Extra: devel
